odoo_backup/config.py
odoo_backup/main.py
odoo_backup/models.py
odoo_backup/rotate.py
odoo_backup/server.py
odoo_backup/tests.py
odoo_backup/utils.py
odoo_backup-0.4.0.dist-info/entry_points.txt
odoo_backup-0.4.0.dist-info/WHEEL
odoo_backup-0.4.0.dist-info/METADATA
odoo_backup-0.4.0.dist-info/RECORD
